{
    "levi": {
        "senha": "levi",
        "senhas": [
            {
                "id": 1,
                "senha": "hgdw",
                "hash": "5f3bf5793be906822be2e946d4738ad12134f931e03683c10fe80cff3ec1932e"
            },
            {
                "id": 2,
                "senha": "fe",
                "hash": "2c9dcded5b6e7e0ee0e0dc6555b45b9ac044efd2b6daa1a1982c3887ddc6d6d4"
            }
        ]
    },
    "jao": {
        "senha": "jao",
        "senhas": [
            {
                "id": 1,
                "senha": "a",
                "hash": "ca978112ca1bbdcafac231b39a23dc4da786eff8147c4e72b9807785afee48bb"
            }
        ]
    },
    "f": {
        "senha": "d",
        "senhas": [
            {
                "id": 1,
                "senha": "ghgg",
                "hash": "a8cd9797bb8b773ebaa4a4cd8877a53c31ef1496254a6fbd373b3fac81d3db3c"
            }
        ]
    },
    "a": {
        "senha": "a",
        "senhas": [
            {
                "id": 16,
                "senha": "a",
                "hash": "ca978112ca1bbdcafac231b39a23dc4da786eff8147c4e72b9807785afee48bb"
            }
        ],
        "plano": "pago"
    }
}